ai/__init__.py
ai/fri3d/__init__.py
ai/fri3d/differentialevolution.py
ai/fri3d/model.py
ai/fri3d/nb.py
ai/fri3d/optimize.py
ai.fri3d-0.0.4.dist-info/METADATA
ai.fri3d-0.0.4.dist-info/WHEEL
ai.fri3d-0.0.4.dist-info/top_level.txt
ai.fri3d-0.0.4.dist-info/RECORD
