Metadata-Version: 2.1
Name: ai.fri3d
Version: 0.0.4
Summary: FRi3D model of coronal mass ejections
Home-page: https://bitbucket.org/isavnin/ai.fri3d
Author: Alexey Isavnin
Author-email: alexey.isavnin@gmail.com
License: MIT
Keywords: research space solar physics science model coronal mass ejection flare CME
Platform: UNKNOWN
Classifier: Development Status :: 5 - Production/Stable
Classifier: Environment :: Console
Classifier: Intended Audience :: Science/Research
Classifier: License :: OSI Approved :: MIT License
Classifier: Programming Language :: Python :: 3
Requires-Dist: numpy
Requires-Dist: scipy
Requires-Dist: matplotlib
Requires-Dist: numba
Requires-Dist: astropy
Requires-Dist: fastdtw
Requires-Dist: ai.cs
